<?xml version="1.0"?>
<!--
 *
 * (c) Kitodo. Key to digital objects e. V. <contact@kitodo.org>
 *
 * This file is part of the Kitodo project.
 *
 * It is licensed under GNU General Public License version 3 or later.
 *
 * For the full copyright and license information, please read the
 * GPL3-License.txt file that was distributed with this source code.
 *
-->
<!DOCTYPE hibernate-mapping PUBLIC
        "-//Hibernate/Hibernate Mapping DTD 3.0//EN"
        "http://www.hibernate.org/dtd/hibernate-mapping-3.0.dtd">

<hibernate-mapping>

	<class name="de.sub.goobi.beans.Regelsatz" table="metadatenkonfigurationen">
		<id name="id" column="MetadatenKonfigurationID" type="integer">
			<generator class="native"/>
		</id>
		
		<property name="titel" column="Titel" type="string"/>
		<property name="datei" column="Datei" type="string"/>
		<property name="orderMetadataByRulesetHibernate" type="java.lang.Boolean">
			<column name="orderMetadataByRuleset" sql-type="bit"/>
		</property>
		
	</class>

</hibernate-mapping>
